interlocutor/VERSION
interlocutor/__init__.py
interlocutor/interlocutor.py
interlocutor/utils.py
interlocutor-0.0.3.dist-info/LICENSE
interlocutor-0.0.3.dist-info/METADATA
interlocutor-0.0.3.dist-info/WHEEL
interlocutor-0.0.3.dist-info/entry_points.txt
interlocutor-0.0.3.dist-info/top_level.txt
interlocutor-0.0.3.dist-info/RECORD
