Metadata-Version: 2.1
Name: interlocutor
Version: 0.0.3
Summary: Interlocutor is a set of utilities for describing the structure and contents of a repository.
Author-email: Zac Miller <zac@informatical.info>
Maintainer-email: Zac Miller <zac@informatical.info>
License: MIT License
Project-URL: Homepage, https://github.com/jzmiller1/interlocutor
Project-URL: Bug Tracker, https://github.com/jzmiller1/interlocutor/issues
Project-URL: Repository, https://github.com/jzmiller1/interlocutor.git
Project-URL: History, https://github.com/jzmiller1/interlocutor/blob/master/HISTORY.md
Keywords: python
Classifier: Programming Language :: Python :: 3
Classifier: License :: OSI Approved :: MIT License
Classifier: Operating System :: OS Independent
Classifier: Development Status :: 2 - Pre-Alpha
Classifier: Intended Audience :: Developers
Requires-Python: >=3.11
License-File: LICENSE
Requires-Dist: pathspec ==0.12.1
Provides-Extra: dev
Requires-Dist: uv <0.3.0,>=0.2.33 ; extra == 'dev'
